{
    "Ar36": {
        "error": 0.00014542893435732246, 
        "error_type": "SEM", 
        "filter_outliers_dict": {
            "filter_outliers": true, 
            "iterations": 1, 
            "std_devs": 10
        }, 
        "fit": "Parabolic", 
        "fn": 399, 
        "include_baseline_error": false, 
        "n": 400, 
        "reviewed": true, 
        "value": 0.0027369964297332527
    }, 
    "Ar37": {
        "error": 0.004905781057163052, 
        "error_type": "SEM", 
        "filter_outliers_dict": {
            "filter_outliers": true, 
            "iterations": 1, 
            "std_devs": 2
        }, 
        "fit": "Linear", 
        "fn": 382, 
        "include_baseline_error": false, 
        "n": 400, 
        "reviewed": true, 
        "value": 0.005735952052253919
    }, 
    "Ar38": {
        "error": 0.0022073934164658798, 
        "error_type": "SEM", 
        "filter_outliers_dict": {
            "filter_outliers": true, 
            "iterations": 1, 
            "std_devs": 2
        }, 
        "fit": "Linear", 
        "fn": 380, 
        "include_baseline_error": false, 
        "n": 400, 
        "reviewed": true, 
        "value": -0.02575154393647408
    }, 
    "Ar39": {
        "error": 0.008974648180890922, 
        "error_type": "SEM", 
        "filter_outliers_dict": {
            "filter_outliers": true, 
            "iterations": 1, 
            "std_devs": 2
        }, 
        "fit": "Parabolic", 
        "fn": 380, 
        "include_baseline_error": false, 
        "n": 400, 
        "reviewed": true, 
        "value": 0.05592680173803902
    }, 
    "Ar40": {
        "error": 0.007221208064098985, 
        "error_type": "SEM", 
        "filter_outliers_dict": {
            "filter_outliers": true, 
            "iterations": 1, 
            "std_devs": 2
        }, 
        "fit": "Parabolic", 
        "fn": 382, 
        "include_baseline_error": false, 
        "n": 400, 
        "reviewed": true, 
        "value": 0.14129426020581817
    }, 
    "Ar41": {
        "error": 0.012575019, 
        "error_type": "SEM", 
        "filter_outliers_dict": {
            "filter_outliers": true, 
            "iterations": 1, 
            "std_devs": 2
        }, 
        "fit": "linear", 
        "value": 0.0699473531
    }
}