{
    "Ar36": {
        "error": 0.00016814467475388106,
        "error_type": "SEM",
        "filter_outliers_dict": {
            "filter_outliers": true,
            "iterations": 1,
            "std_devs": 2
        },
        "fit": "Parabolic",
        "fn": 270,
        "include_baseline_error": false,
        "n": 280,
        "reviewed": true,
        "value": 0.002412270987784391
    },
    "Ar37": {
        "error": 0.0054092429928546204,
        "error_type": "SEM",
        "filter_outliers_dict": {
            "filter_outliers": true,
            "iterations": 1,
            "std_devs": 2
        },
        "fit": "Linear",
        "fn": 269,
        "include_baseline_error": false,
        "n": 280,
        "reviewed": true,
        "value": -0.014035139284391828
    },
    "Ar38": {
        "error": 0.002711164394244927,
        "error_type": "SEM",
        "filter_outliers_dict": {
            "filter_outliers": true,
            "iterations": 1,
            "std_devs": 2
        },
        "fit": "Linear",
        "fn": 268,
        "include_baseline_error": false,
        "n": 280,
        "reviewed": true,
        "value": -0.03310678524259281
    },
    "Ar39": {
        "error": 0.011159922422681205,
        "error_type": "SEM",
        "filter_outliers_dict": {
            "filter_outliers": true,
            "iterations": 1,
            "std_devs": 2
        },
        "fit": "Parabolic",
        "fn": 270,
        "include_baseline_error": false,
        "n": 280,
        "reviewed": true,
        "value": 0.0402868346807559
    },
    "Ar40": {
        "error": 0.008898601771764438,
        "error_type": "SEM",
        "filter_outliers_dict": {
            "filter_outliers": true,
            "iterations": 1,
            "std_devs": 2
        },
        "fit": "Parabolic",
        "fn": 268,
        "include_baseline_error": false,
        "n": 280,
        "reviewed": true,
        "value": 0.12055187138727658
    },
    "Ar41": {
        "error": 0.014511822265337482,
        "error_type": "SEM",
        "filter_outliers_dict": {
            "filter_outliers": true,
            "iterations": 1,
            "std_devs": 2
        },
        "fit": "linear",
        "value": 0.04334643967379913
    }
}