{
    "Ar36":{
        "error":0.0016533456,
        "error_type":"SEM",
        "filter_outliers_dict":{
            "filter_outliers":true,
            "iterations":1,
            "std_devs":2
        },
        "fit":"Parabolic",
        "value":0.9555290083
    },
    "Ar37":{
        "error":0.0049705584,
        "error_type":"SEM",
        "filter_outliers_dict":{
            "filter_outliers":true,
            "iterations":1,
            "std_devs":2
        },
        "fit":"linear",
        "value":0.0099748185
    },
    "Ar38":{
        "error":0.0021673018,
        "error_type":"SEM",
        "filter_outliers_dict":{
            "filter_outliers":true,
            "iterations":1,
            "std_devs":2
        },
        "fit":"linear",
        "value":0.1529156676
    },
    "Ar39":{
        "error":0.0083946941,
        "error_type":"SEM",
        "filter_outliers_dict":{
            "filter_outliers":true,
            "iterations":1,
            "std_devs":2
        },
        "fit":"Parabolic",
        "value":0.0441654583
    },
    "Ar40":{
        "error":0.0213653807,
        "error_type":"SEM",
        "filter_outliers_dict":{
            "filter_outliers":true,
            "iterations":1,
            "std_devs":2
        },
        "fit":"Parabolic",
        "value":283.1567067111
    },
    "Ar41":{
        "error":0.0114738967,
        "error_type":"SEM",
        "filter_outliers_dict":{
            "filter_outliers":true,
            "iterations":1,
            "std_devs":2
        },
        "fit":"linear",
        "value":0.0711781501
    }
}