{
    "Ar36":{
        "error":0.0017599552,
        "error_type":"SEM",
        "filter_outliers_dict":{
            "filter_outliers":true,
            "iterations":1,
            "std_devs":2
        },
        "fit":"Parabolic",
        "value":0.9176725731
    },
    "Ar37":{
        "error":0.0047675095,
        "error_type":"SEM",
        "filter_outliers_dict":{
            "filter_outliers":true,
            "iterations":1,
            "std_devs":2
        },
        "fit":"linear",
        "value":0.0012185702
    },
    "Ar38":{
        "error":0.0022066413,
        "error_type":"SEM",
        "filter_outliers_dict":{
            "filter_outliers":true,
            "iterations":1,
            "std_devs":2
        },
        "fit":"linear",
        "value":0.1462472446
    },
    "Ar39":{
        "error":0.0087152711,
        "error_type":"SEM",
        "filter_outliers_dict":{
            "filter_outliers":true,
            "iterations":1,
            "std_devs":2
        },
        "fit":"Parabolic",
        "value":0.0447181046
    },
    "Ar40":{
        "error":0.0210193069,
        "error_type":"SEM",
        "filter_outliers_dict":{
            "filter_outliers":true,
            "iterations":1,
            "std_devs":2
        },
        "fit":"Parabolic",
        "value":270.9367910832
    },
    "Ar41":{
        "error":0.010972545,
        "error_type":"SEM",
        "filter_outliers_dict":{
            "filter_outliers":true,
            "iterations":1,
            "std_devs":2
        },
        "fit":"linear",
        "value":0.0634568742
    }
}