{
    "Ar36":{
        "error":0.0017435059,
        "error_type":"SEM",
        "filter_outliers_dict":{
            "filter_outliers":true,
            "iterations":1,
            "std_devs":2
        },
        "fit":"Parabolic",
        "value":0.9585723033
    },
    "Ar37":{
        "error":0.0057691503,
        "error_type":"SEM",
        "filter_outliers_dict":{
            "filter_outliers":true,
            "iterations":1,
            "std_devs":2
        },
        "fit":"linear",
        "value":-0.0040058335
    },
    "Ar38":{
        "error":0.0026902457,
        "error_type":"SEM",
        "filter_outliers_dict":{
            "filter_outliers":true,
            "iterations":1,
            "std_devs":2
        },
        "fit":"linear",
        "value":0.1513334711
    },
    "Ar39":{
        "error":0.010047355,
        "error_type":"SEM",
        "filter_outliers_dict":{
            "filter_outliers":true,
            "iterations":1,
            "std_devs":2
        },
        "fit":"Parabolic",
        "value":0.0614204498
    },
    "Ar40":{
        "error":0.0242893801,
        "error_type":"SEM",
        "filter_outliers_dict":{
            "filter_outliers":true,
            "iterations":1,
            "std_devs":2
        },
        "fit":"Parabolic",
        "value":283.8310141862
    },
    "Ar41":{
        "error":0.0129425865,
        "error_type":"SEM",
        "filter_outliers_dict":{
            "filter_outliers":true,
            "iterations":1,
            "std_devs":2
        },
        "fit":"linear",
        "value":0.0608982564
    }
}