{
    "AX":{
        "error":0.0045335958,
        "error_type":"SEM",
        "filter_outliers_dict":{
            "filter_outliers":true,
            "iterations":1,
            "std_devs":2
        },
        "fit":"average",
        "value":0.0184681172
    },
    "CDD":{
        "error":0.0000032639,
        "error_type":"SEM",
        "filter_outliers_dict":{
            "filter_outliers":true,
            "iterations":1,
            "std_devs":10
        },
        "fit":"average",
        "value":0.0000088617
    },
    "H1":{
        "error":0.0035619985,
        "error_type":"SEM",
        "filter_outliers_dict":{
            "filter_outliers":true,
            "iterations":1,
            "std_devs":2
        },
        "fit":"average",
        "value":0.0138660427
    },
    "H2":{
        "error":0.0104792988,
        "error_type":"SEM",
        "filter_outliers_dict":{
            "filter_outliers":true,
            "iterations":1,
            "std_devs":2
        },
        "fit":"average",
        "value":0.0133222543
    },
    "L1":{
        "error":0.0016300777,
        "error_type":"SEM",
        "filter_outliers_dict":{
            "filter_outliers":true,
            "iterations":1,
            "std_devs":2
        },
        "fit":"average",
        "value":-0.0434589748
    },
    "L2":{
        "error":0.0046332208,
        "error_type":"SEM",
        "filter_outliers_dict":{
            "filter_outliers":true,
            "iterations":1,
            "std_devs":2
        },
        "fit":"average",
        "value":-0.0352286333
    }
}